{
  "AF": "AF", "AL": "AL", "AG": "DZ", "AN": "AD", "AO": "AO",
  "AC": "AG", "AR": "AR", "AM": "AM", "AS": "AU", "AU": "AT",
  "AJ": "AZ", "BF": "BS", "BA": "BH", "BG": "BD", "BB": "BB",
  "BO": "BY", "BE": "BE", "BH": "BZ", "BN": "BJ", "BT": "BT",
  "BL": "BO", "BK": "BA", "BC": "BW", "BR": "BR", "BX": "BN",
  "BU": "BG", "UV": "BF", "BY": "BI", "CV": "CV", "CB": "KH",
  "CM": "CM", "CA": "CA", "CT": "CF", "CD": "TD", "CI": "CL",
  "CH": "CN", "CO": "CO", "CN": "KM", "CF": "CG", "CG": "CD",
  "CS": "CR", "HR": "HR", "CU": "CU", "CY": "CY", "EZ": "CZ",
  "DA": "DK", "DJ": "DJ", "DO": "DM", "DR": "DO", "EC": "EC",
  "EG": "EG", "ES": "SV", "EK": "GQ", "ER": "ER", "EN": "EE",
  "WZ": "SZ", "ET": "ET", "FJ": "FJ", "FI": "FI", "FR": "FR",
  "GB": "GA", "GA": "GM", "GG": "GE", "GM": "DE", "GH": "GH",
  "GR": "GR", "GJ": "GD", "GT": "GT", "GV": "GN", "PU": "GW",
  "GY": "GY", "HA": "HT", "HO": "HN", "HU": "HU", "IC": "IS",
  "IN": "IN", "ID": "ID", "IR": "IR", "IZ": "IQ", "EI": "IE",
  "IS": "IL", "IT": "IT", "IV": "CI", "JM": "JM", "JA": "JP",
  "JO": "JO", "KZ": "KZ", "KE": "KE", "KR": "KI", "KN": "KP",
  "KS": "KR", "KU": "KW", "KG": "KG", "LA": "LA", "LG": "LV",
  "LE": "LB", "LT": "LS", "LI": "LR", "LY": "LY", "LS": "LI",
  "LH": "LT", "LU": "LU", "MA": "MG", "MI": "MW", "MY": "MY",
  "MV": "MV", "ML": "ML", "MT": "MT", "MR": "MR", "MP": "MU",
  "MX": "MX", "MD": "MD", "MN": "MC", "MG": "MN", "MJ": "ME",
  "MO": "MA", "MZ": "MZ", "BM": "MM", "WA": "NA", "NP": "NP",
  "NL": "NL", "NZ": "NZ", "NU": "NI", "NG": "NE", "NI": "NG",
  "MK": "MK", "NO": "NO", "MU2": "OM", "PK": "PK", "PM": "PA",
  "PP": "PG", "PA": "PY", "PE": "PE", "RP": "PH", "PL": "PL",
  "PO": "PT", "QA": "QA", "RO": "RO", "RS": "RU", "RW": "RW",
  "ST": "LC", "WS": "WS", "SA": "SA", "SG": "SN", "RI": "RS",
  "SL": "SL", "SN": "SG", "LO": "SK", "SI": "SI", "BP": "SB",
  "SO": "SO", "SF": "ZA", "OD": "SS", "SP": "ES", "CE": "LK",
  "SU": "SD", "NS": "SR", "SW": "SE", "SZ": "CH", "SY": "SY",
  "TW": "TW", "TI": "TJ", "TZ": "TZ", "TH": "TH", "TT": "TL",
  "TO": "TG", "TN": "TO", "TD": "TT", "TS": "TN", "TU": "TR",
  "TX": "TM", "UG": "UG", "UP": "UA", "AE": "AE", "UK": "GB",
  "US": "US", "UY": "UY", "UZ": "UZ", "NH": "VU", "VE": "VE",
  "VM": "VN", "YM": "YE", "ZA": "ZM", "ZI": "ZW", "GZ": "PS",
  "WI": "EH", "KV": "XK"
}
